prolothar_queue_mining/__init__.py
prolothar_queue_mining/inference/__init__.py
prolothar_queue_mining/inference/queue/__init__.py
prolothar_queue_mining/inference/queue/fcfs_c_one_throughput.py
prolothar_queue_mining/inference/queue/keith_ahner_hill.py
prolothar_queue_mining/inference/queue/naive_brute_force.cp311-win_amd64.pyd
prolothar_queue_mining/inference/queue/naive_brute_force.cpp
prolothar_queue_mining/inference/queue/naive_brute_force.pyx
prolothar_queue_mining/inference/queue/queue_miner.py
prolothar_queue_mining/inference/queue/times.cp311-win_amd64.pyd
prolothar_queue_mining/inference/queue/times.cpp
prolothar_queue_mining/inference/queue/times.pxd
prolothar_queue_mining/inference/queue/times.pyx
prolothar_queue_mining/inference/queue/utils.py
prolothar_queue_mining/inference/queue/batch/__init__.py
prolothar_queue_mining/inference/queue/batch/largest_gap_batch_miner.py
prolothar_queue_mining/inference/queue/batch/psm_batch_miner.py
prolothar_queue_mining/inference/queue/cuemin/__init__.py
prolothar_queue_mining/inference/queue/cuemin/cuemin.py
prolothar_queue_mining/inference/queue/cuemin/mdl_batch_size_distribution.py
prolothar_queue_mining/inference/queue/cuemin/mdl_score.py
prolothar_queue_mining/inference/queue/cuemin/mdl_service_time.py
prolothar_queue_mining/inference/queue/cuemin/record.py
prolothar_queue_mining/inference/queue/cuemin/search_strategy/__init__.py
prolothar_queue_mining/inference/queue/cuemin/search_strategy/adaptive_stepsize.py
prolothar_queue_mining/inference/queue/cuemin/search_strategy/linear.py
prolothar_queue_mining/inference/queue/cuemin/search_strategy/nsection.py
prolothar_queue_mining/inference/queue/cuemin/search_strategy/search_strategy.py
prolothar_queue_mining/inference/queue/cuemin/search_strategy/simulated_annealing.py
prolothar_queue_mining/inference/queue/cuemin/search_strategy/weighted_sampling.py
prolothar_queue_mining/inference/queue/nr_of_servers/__init__.py
prolothar_queue_mining-3.0.0.dist-info/LICENSE
prolothar_queue_mining-3.0.0.dist-info/METADATA
prolothar_queue_mining-3.0.0.dist-info/WHEEL
prolothar_queue_mining-3.0.0.dist-info/top_level.txt
prolothar_queue_mining-3.0.0.dist-info/RECORD
