Metadata-Version: 2.1
Name: prolothar-queue-mining
Version: 3.0.0
Summary: algorithms for queue mining from event logs
Home-page: https://gitlab.dillinger.de/KI/DataScience/processmining/prolothar-queue-mining
Author: Boris Wiegand
Author-email: boris.wiegand@stahl-holding-saar.de
Classifier: Programming Language :: Python :: 3
Classifier: Programming Language :: Python :: 3.11
License-File: LICENSE
Requires-Dist: prolothar-common >=6.1.0
Requires-Dist: methodtools ==0.4.7
Requires-Dist: statsmodels ==0.14.1
Requires-Dist: distfit ==1.7.3
Requires-Dist: kmeans1d ==0.3.1
Requires-Dist: simanneal ==0.5.0
Requires-Dist: tensorflow
